classification_model/VERSION
classification_model/__init__.py
classification_model/config.yaml
classification_model/pipeline.py
classification_model/predict.py
classification_model/train_pipeline.py
classification_model/config/__init__.py
classification_model/config/core.py
classification_model/datasets/__init__.py
classification_model/datasets/test.csv
classification_model/datasets/train.csv
classification_model/preprocessing/__init__.py
classification_model/preprocessing/data_manager.py
classification_model/preprocessing/modelevaluation.py
classification_model/preprocessing/preprocessing.py
classification_model/preprocessing/validation.py
classification_model/trained_models/__init__.py
classification_model/trained_models/classification_model_output_v1.0.3.joblib
classification_model/trained_models/classification_model_output_v1.0.3.tflite
classification_model/trained_models/classification_model_output_v_preprocess1.0.3.joblib
complaintClassify-1.0.3.dist-info/LICENSE.txt
complaintClassify-1.0.3.dist-info/METADATA
complaintClassify-1.0.3.dist-info/WHEEL
complaintClassify-1.0.3.dist-info/top_level.txt
complaintClassify-1.0.3.dist-info/RECORD
