Metadata-Version: 2.1
Name: complaintClassify
Version: 1.0.3
Summary: Classification of consumer complaint.
Home-page: https://github.com/KrSiddhartha/MLPipeline/
Author: KumarSiddhartha
Author-email: kr.siddhartha91@gmail.com
License: BSD-3
Platform: UNKNOWN
Classifier: License :: OSI Approved :: MIT License
Classifier: Programming Language :: Python :: 3
Classifier: Operating System :: OS Independent
Requires-Python: ==3.8.5
License-File: LICENSE.txt
Requires-Dist: nltk (==3.6.7)
Requires-Dist: numpy (==1.19.5)
Requires-Dist: pandas (==1.4.0)
Requires-Dist: pydantic (<1.9.0,>=1.8.1)
Requires-Dist: scikit-learn (==1.0.2)
Requires-Dist: strictyaml (==1.6.1)
Requires-Dist: tflite-runtime (<2.8.0,>=2.5.0)
